server/__init__.py
server/api.py
server/templates/index.html
server/templates/queue.html
xq/__init__.py
xq/message.py
xq/queue.py
xq/worker.py
xqueue-0.2.3.dist-info/licenses/LICENSE
xqueue-0.2.3.dist-info/METADATA
xqueue-0.2.3.dist-info/WHEEL
xqueue-0.2.3.dist-info/entry_points.txt
xqueue-0.2.3.dist-info/top_level.txt
xqueue-0.2.3.dist-info/RECORD
