Metadata-Version: 2.4
Name: xqueue
Version: 0.2.3
Summary: A distributed task queue with cron scheduling built on top of Redis
Home-page: https://github.com/chishui/xq
Author: chishui
Author-email: chishui2@gmail.com
Project-URL: Bug Reports, https://github.com/chishui/xq/issues
Project-URL: Source, https://github.com/chishui/xq
Keywords: queue,redis,messaging,cron,scheduler,task,distributed
Classifier: Development Status :: 4 - Beta
Classifier: Intended Audience :: Developers
Classifier: Topic :: Software Development :: Libraries :: Python Modules
Classifier: Topic :: System :: Distributed Computing
Classifier: License :: OSI Approved :: MIT License
Classifier: Programming Language :: Python :: 3
Classifier: Programming Language :: Python :: 3.8
Classifier: Programming Language :: Python :: 3.9
Classifier: Programming Language :: Python :: 3.10
Classifier: Programming Language :: Python :: 3.11
Classifier: Programming Language :: Python :: 3 :: Only
Requires-Python: >=3.8, <4
License-File: LICENSE
Requires-Dist: redis>=5.0.0
Requires-Dist: croniter>=6.0.0
Requires-Dist: jsonpickle>=3.0.0
Requires-Dist: python-dateutil>=2.9.0
Requires-Dist: pytz>=2025.0
Provides-Extra: server
Requires-Dist: fastapi>=0.100.0; extra == "server"
Requires-Dist: uvicorn>=0.27.0; extra == "server"
Requires-Dist: jinja2>=3.1.0; extra == "server"
Requires-Dist: python-multipart; extra == "server"
Requires-Dist: websockets>=15.0.0; extra == "server"
Dynamic: author
Dynamic: author-email
Dynamic: classifier
Dynamic: description
Dynamic: description-content-type
Dynamic: home-page
Dynamic: keywords
Dynamic: license-file
Dynamic: project-url
Dynamic: provides-extra
Dynamic: requires-dist
Dynamic: requires-python
Dynamic: summary
